auth_util/__init__.py
auth_util/json_web_token.py
auth_util/middleware.py
auth_util/password.py
test/__init__.py
test/test_jwt.py
test/test_password.py
auth_util-0.1.1.dist-info/METADATA
auth_util-0.1.1.dist-info/WHEEL
auth_util-0.1.1.dist-info/top_level.txt
auth_util-0.1.1.dist-info/RECORD
