Metadata-Version: 2.1
Name: auth-util
Version: 0.1.1
Summary: Password and jwt manager
Home-page: https://github.com/StevenLianaL/auth-util
Author: Steven Wang
Author-email: brightstar8284@icloud.com
License: UNKNOWN
Platform: UNKNOWN
Classifier: Programming Language :: Python :: 3
Classifier: License :: OSI Approved :: MIT License
Requires-Dist: passlib (>=1.7.4)
Requires-Dist: bcrypt (>=3.2.0)
Requires-Dist: PyJWT (>=2.0.1)
Requires-Dist: starlette (>=0.13.6)
Requires-Dist: cryptography (>=3.3.1)
